nullpom/__init__.py
nullpom/main.py
nullpom-0.1.0.dist-info/WHEEL
nullpom-0.1.0.dist-info/METADATA
nullpom-0.1.0.dist-info/RECORD
