Metadata-Version: 2.1
Name: nullpom
Version: 0.1.0
Summary: Library to easily run Null Importances.
Home-page: https://github.com/tenajima/nullpom
License: MIT
Keywords: null importance,feature selection,importance,kaggle
Author: tenajima
Author-email: tenajima@gmail.com
Requires-Python: >=3.7.1,<4.0.0
Classifier: License :: OSI Approved :: MIT License
Classifier: Programming Language :: Python :: 3
Classifier: Programming Language :: Python :: 3.8
Classifier: Programming Language :: Python :: 3.9
Requires-Dist: lightgbm (>=3.1.1,<4.0.0)
Requires-Dist: matplotlib (==3.2.2)
Requires-Dist: pandas (>=1.1,<1.2)
Requires-Dist: scikit-learn (>=0.24.1,<0.25.0)
Project-URL: Documentation, https://github.com/tenajima/nullpom
Project-URL: Repository, https://github.com/tenajima/nullpom
